hawk_backtester-0.4.0.dist-info/METADATA
hawk_backtester-0.4.0.dist-info/WHEEL
hawk_backtester-0.4.0.dist-info/licenses/LICENSE
hawk_backtester/__init__.py
hawk_backtester/hawk_backtester.cpython-311-darwin.so
hawk_backtester-0.4.0.dist-info/RECORD
